Workbook

Sheet Employee Record
A1: Employee ID | B1: First Name | C1: Last Name | D1: Department | E1: Job Title | F1: Performance Score | G1: Date of Birth | H1: Hire Date | I1: Salary | J1: Comments | K1: Performance Grade | L1: Department Code | M1: Full Name | N1: Length of Emp ID | O1: Employee Age | P1: Months | Q1: Employee Year of Service | R1: Eligibility Status | S1: Sales/IT | T1: Bonus | V1: Bonus Rate= | W1: 0.5
A2: EMP001 | B2: Michael | C2: Wagner | D2: IT | E2: IT Support | F2: 85 | G2: 33693 | H2: 45252 | I2: 8352 | J2: =IF(F2>=50,"Pass","Fail") -> Pass | K2: {=IFS(F2>=90,"Excellent",F2>=70,"Good",F2>=50,"Average",F2<50,"Poor")} -> Good | L2: =LEFT(D2,3) -> IT | M2: =CONCATENATE(B2," ",C2) -> Michael Wagner | N2: =LEN(A2) -> 6 | O2: =DATEDIF(G2,TODAY(),"y") -> 33 | P2: =TEXT(H2,"mmmm") -> November | Q2: =DATEDIF(H2,TODAY(),"y") -> 1 | R2: =IF(AND(O2>25,Q2>2),"Eligible","Not Eligible") -> Not Eligible | S2: =IF(OR(D2=$D$7,D2=$D$2),"True","False") -> True | T2: =$W$1*I2 -> 4176
A3: EMP002 | B3: Adam | C3: Henry | D3: Finance | E3: Accountant | F3: 93 | G3: 32359 | H3: 45552 | I3: 5982 | J3: =IF(F3>=50,"Pass","Fail") -> Pass | K3: {=IFS(F3>=90,"Excellent",F3>=70,"Good",F3>=50,"Average",F3<50,"Poor")} -> Excellent | L3: =LEFT(D3,3) -> Fin | M3: =CONCATENATE(B3," ",C3) -> Adam Henry | N3: =LEN(A3) -> 6 | O3: =DATEDIF(G3,TODAY(),"y") -> 37 | P3: =TEXT(H3,"mmmm") -> September | Q3: =DATEDIF(H3,TODAY(),"y") -> 1 | R3: =IF(AND(O3>25,Q3>2),"Eligible","Not Eligible") -> Not Eligible | S3: =IF(OR(D3=$D$7,D3=$D$2),"True","False") -> False | T3: =$W$1*I3 -> 2991
A4: EMP003 | B4: Gregory | C4: Rojas | D4: HR | E4: HR Assistant | F4: 37 | G4: 36559 | H4: 43269 | I4: 5767 | J4: =IF(F4>=50,"Pass","Fail") -> Fail | K4: {=IFS(F4>=90,"Excellent",F4>=70,"Good",F4>=50,"Average",F4<50,"Poor")} -> Poor | L4: =LEFT(D4,3) -> HR | M4: =CONCATENATE(B4," ",C4) -> Gregory Rojas | N4: =LEN(A4) -> 6 | O4: =DATEDIF(G4,TODAY(),"y") -> 25 | P4: =TEXT(H4,"mmmm") -> June | Q4: =DATEDIF(H4,TODAY(),"y") -> 7 | R4: =IF(AND(O4>25,Q4>2),"Eligible","Not Eligible") -> Not Eligible | S4: =IF(OR(D4=$D$7,D4=$D$2),"True","False") -> False | T4: =$W$1*I4 -> 2883.5
A5: EMP004 | B5: Joseph | C5: Estrada | D5: Finance | E5: Financial Analyst | F5: 87 | G5: 31829 | H5: 43487 | I5: 5622 | J5: =IF(F5>=50,"Pass","Fail") -> Pass | K5: {=IFS(F5>=90,"Excellent",F5>=70,"Good",F5>=50,"Average",F5<50,"Poor")} -> Good | L5: =LEFT(D5,3) -> Fin | M5: =CONCATENATE(B5," ",C5) -> Joseph Estrada | N5: =LEN(A5) -> 6 | O5: =DATEDIF(G5,TODAY(),"y") -> 38 | P5: =TEXT(H5,"mmmm") -> January | Q5: =DATEDIF(H5,TODAY(),"y") -> 6 | R5: =IF(AND(O5>25,Q5>2),"Eligible","Not Eligible") -> Eligible | S5: =IF(OR(D5=$D$7,D5=$D$2),"True","False") -> False | T5: =$W$1*I5 -> 2811
A6: EMP005 | B6: Tracie | C6: Collins | D6: Finance | E6: Accountant | F6: 63 | G6: 37665 | H6: 44509 | I6: 7037 | J6: =IF(F6>=50,"Pass","Fail") -> Pass | K6: {=IFS(F6>=90,"Excellent",F6>=70,"Good",F6>=50,"Average",F6<50,"Poor")} -> Average | L6: =LEFT(D6,3) -> Fin | M6: =CONCATENATE(B6," ",C6) -> Tracie Collins | N6: =LEN(A6) -> 6 | O6: =DATEDIF(G6,TODAY(),"y") -> 22 | P6: =TEXT(H6,"mmmm") -> November | Q6: =DATEDIF(H6,TODAY(),"y") -> 3 | R6: =IF(AND(O6>25,Q6>2),"Eligible","Not Eligible") -> Not Eligible | S6: =IF(OR(D6=$D$7,D6=$D$2),"True","False") -> False | T6: =$W$1*I6 -> 3518.5
A7: EMP006 | B7: Jonathon | C7: Wright | D7: Sales | E7: Sales Rep | F7: 35 | G7: 37209 | H7: 44779 | I7: 4157 | J7: =IF(F7>=50,"Pass","Fail") -> Fail | K7: {=IFS(F7>=90,"Excellent",F7>=70,"Good",F7>=50,"Average",F7<50,"Poor")} -> Poor | L7: =LEFT(D7,3) -> Sal | M7: =CONCATENATE(B7," ",C7) -> Jonathon Wright | N7: =LEN(A7) -> 6 | O7: =DATEDIF(G7,TODAY(),"y") -> 23 | P7: =TEXT(H7,"mmmm") -> August | Q7: =DATEDIF(H7,TODAY(),"y") -> 3 | R7: =IF(AND(O7>25,Q7>2),"Eligible","Not Eligible") -> Not Eligible | S7: =IF(OR(D7=$D$7,D7=$D$2),"True","False") -> True | T7: =$W$1*I7 -> 2078.5
A8: EMP007 | B8: Christina | C8: Haynes | D8: IT | E8: IT Support | F8: 100 | G8: 34445 | H8: 43110 | I8: 8025 | J8: =IF(F8>=50,"Pass","Fail") -> Pass | K8: {=IFS(F8>=90,"Excellent",F8>=70,"Good",F8>=50,"Average",F8<50,"Poor")} -> Excellent | L8: =LEFT(D8,3) -> IT | M8: =CONCATENATE(B8," ",C8) -> Christina Haynes | N8: =LEN(A8) -> 6 | O8: =DATEDIF(G8,TODAY(),"y") -> 31 | P8: =TEXT(H8,"mmmm") -> January | Q8: =DATEDIF(H8,TODAY(),"y") -> 7 | R8: =IF(AND(O8>25,Q8>2),"Eligible","Not Eligible") -> Eligible | S8: =IF(OR(D8=$D$7,D8=$D$2),"True","False") -> True | T8: =$W$1*I8 -> 4012.5
A9: EMP008 | B9: Kelly | C9: Henry | D9: Sales | E9: Account Exec | F9: 65 | G9: 36461 | H9: 44524 | I9: 4533 | J9: =IF(F9>=50,"Pass","Fail") -> Pass | K9: {=IFS(F9>=90,"Excellent",F9>=70,"Good",F9>=50,"Average",F9<50,"Poor")} -> Average | L9: =LEFT(D9,3) -> Sal | M9: =CONCATENATE(B9," ",C9) -> Kelly Henry | N9: =LEN(A9) -> 6 | O9: =DATEDIF(G9,TODAY(),"y") -> 26 | P9: =TEXT(H9,"mmmm") -> November | Q9: =DATEDIF(H9,TODAY(),"y") -> 3 | R9: =IF(AND(O9>25,Q9>2),"Eligible","Not Eligible") -> Eligible | S9: =IF(OR(D9=$D$7,D9=$D$2),"True","False") -> True | T9: =$W$1*I9 -> 2266.5
A10: EMP009 | B10: Mary | C10: Torres | D10: Finance | E10: Accountant | F10: 64 | G10: 34267 | H10: 42130 | I10: 9480 | J10: =IF(F10>=50,"Pass","Fail") -> Pass | K10: {=IFS(F10>=90,"Excellent",F10>=70,"Good",F10>=50,"Average",F10<50,"Poor")} -> Average | L10: =LEFT(D10,3) -> Fin | M10: =CONCATENATE(B10," ",C10) -> Mary Torres | N10: =LEN(A10) -> 6 | O10: =DATEDIF(G10,TODAY(),"y") -> 32 | P10: =TEXT(H10,"mmmm") -> May | Q10: =DATEDIF(H10,TODAY(),"y") -> 10 | R10: =IF(AND(O10>25,Q10>2),"Eligible","Not Eligible") -> Eligible | S10: =IF(OR(D10=$D$7,D10=$D$2),"True","False") -> False | T10: =$W$1*I10 -> 4740
A11: EMP010 | B11: David | C11: Rodriguez | D11: Finance | E11: Accountant | F11: 53 | G11: 37359 | H11: 42780 | I11: 7771 | J11: =IF(F11>=50,"Pass","Fail") -> Pass | K11: {=IFS(F11>=90,"Excellent",F11>=70,"Good",F11>=50,"Average",F11<50,"Poor")} -> Average | L11: =LEFT(D11,3) -> Fin | M11: =CONCATENATE(B11," ",C11) -> David Rodriguez | N11: =LEN(A11) -> 6 | O11: =DATEDIF(G11,TODAY(),"y") -> 23 | P11: =TEXT(H11,"mmmm") -> February | Q11: =DATEDIF(H11,TODAY(),"y") -> 8 | R11: =IF(AND(O11>25,Q11>2),"Eligible","Not Eligible") -> Not Eligible | S11: =IF(OR(D11=$D$7,D11=$D$2),"True","False") -> False | T11: =$W$1*I11 -> 3885.5
A12: EMP011 | B12: John | C12: Cole | D12: Finance | E12: Accountant | F12: 62 | G12: 34343 | H12: 43058 | I12: 5076 | J12: =IF(F12>=50,"Pass","Fail") -> Pass | K12: {=IFS(F12>=90,"Excellent",F12>=70,"Good",F12>=50,"Average",F12<50,"Poor")} -> Average | L12: =LEFT(D12,3) -> Fin | M12: =CONCATENATE(B12," ",C12) -> John Cole | N12: =LEN(A12) -> 6 | O12: =DATEDIF(G12,TODAY(),"y") -> 31 | P12: =TEXT(H12,"mmmm") -> November | Q12: =DATEDIF(H12,TODAY(),"y") -> 7 | R12: =IF(AND(O12>25,Q12>2),"Eligible","Not Eligible") -> Eligible | S12: =IF(OR(D12=$D$7,D12=$D$2),"True","False") -> False | T12: =$W$1*I12 -> 2538
A13: EMP012 | B13: Christina | C13: Levine | D13: HR | E13: HR Assistant | F13: 82 | G13: 32252 | H13: 41699 | I13: 4696 | J13: =IF(F13>=50,"Pass","Fail") -> Pass | K13: {=IFS(F13>=90,"Excellent",F13>=70,"Good",F13>=50,"Average",F13<50,"Poor")} -> Good | L13: =LEFT(D13,3) -> HR | M13: =CONCATENATE(B13," ",C13) -> Christina Levine | N13: =LEN(A13) -> 6 | O13: =DATEDIF(G13,TODAY(),"y") -> 37 | P13: =TEXT(H13,"mmmm") -> March | Q13: =DATEDIF(H13,TODAY(),"y") -> 11 | R13: =IF(AND(O13>25,Q13>2),"Eligible","Not Eligible") -> Eligible | S13: =IF(OR(D13=$D$7,D13=$D$2),"True","False") -> False | T13: =$W$1*I13 -> 2348
... A201: EMP200 | B201: Lisa | C201: Smith | D201: Marketing | E201: Marketing Officer | F201: 45 | G201: 32876 | H201: 44268 | I201: 6821 | J201: =IF(F201>=50,"Pass","Fail") -> Fail | K201: {=IFS(F201>=90,"Excellent",F201>=70,"Good",F201>=50,"Average",F201<50,"Poor")} -> Poor | L201: =LEFT(D201,3) -> Mar | M201: =CONCATENATE(B201," ",C201) -> Lisa Smith | N201: =LEN(A201) -> 6 | O201: =DATEDIF(G201,TODAY(),"y") -> 35 | P201: =TEXT(H201,"mmmm") -> March | Q201: =DATEDIF(H201,TODAY(),"y") -> 4 | R201: =IF(AND(O201>25,Q201>2),"Eligible","Not Eligible") -> Eligible | S201: =IF(OR(D201=$D$7,D201=$D$2),"True","False") -> False | T201: =$W$1*I201 -> 3410.5

Sheet Filtering&Sorting
A1: Employee ID | B1: First Name | C1: Last Name | D1: Department | E1: Job Title | F1: Performance Score | G1: Date of Birth | H1: Hire Date | I1: Salary | J1: Comments | K1: Performance Grade | L1: Dept Code | M1: Full Name | N1: Length of Emp ID | O1: Employee Age | P1: Months | Q1: Employee Year of Service | R1: Eligibily Status | S1: Sales/IT
A2: EMP156 | B2: Brittany | C2: Collier | D2: Sales | E2: Sales Manager | F2: 68 | G2: 35648 | H2: 41258 | I2: 6485 | J2: =IF(F2>=50,"Pass","Fail") -> Pass | K2: {=IFS(F2>=90,"Excellent",F2>=70,"Good",F2>=50,"Average",F2<50,"Poor")} -> Average | L2: =LEFT(D2,3) -> Sal | M2: =CONCATENATE(B2," ",C2) -> Brittany Collier | N2: =LEN(A2) -> 6 | O2: =DATEDIF(G2,TODAY(),"y") -> 28 | P2: =TEXT(H2,"mmmm") -> December | Q2: =DATEDIF(H2,TODAY(),"y") -> 12 | R2: =IF(AND(O2>25,Q2>2),"Eligible","Not Eligible") -> Eligible | S2: =IF(OR(D2=$D$7,D2=$D$2),"True","False") -> True
A3: EMP064 | B3: Jennifer | C3: Hampton | D3: Sales | E3: Sales Manager | F3: 76 | G3: 34883 | H3: 41308 | I3: 7859 | J3: =IF(F3>=50,"Pass","Fail") -> Pass | K3: {=IFS(F3>=90,"Excellent",F3>=70,"Good",F3>=50,"Average",F3<50,"Poor")} -> Good | L3: =LEFT(D3,3) -> Sal | M3: =CONCATENATE(B3," ",C3) -> Jennifer Hampton | N3: =LEN(A3) -> 6 | O3: =DATEDIF(G3,TODAY(),"y") -> 30 | P3: =TEXT(H3,"mmmm") -> February | Q3: =DATEDIF(H3,TODAY(),"y") -> 12 | R3: =IF(AND(O3>25,Q3>2),"Eligible","Not Eligible") -> Eligible | S3: =IF(OR(D3=$D$7,D3=$D$2),"True","False") -> True
A4: EMP017 | B4: Teresa | C4: Gutierrez | D4: IT | E4: IT Support | F4: 87 | G4: 31285 | H4: 41312 | I4: 6214 | J4: =IF(F4>=50,"Pass","Fail") -> Pass | K4: {=IFS(F4>=90,"Excellent",F4>=70,"Good",F4>=50,"Average",F4<50,"Poor")} -> Good | L4: =LEFT(D4,3) -> IT | M4: =CONCATENATE(B4," ",C4) -> Teresa Gutierrez | N4: =LEN(A4) -> 6 | O4: =DATEDIF(G4,TODAY(),"y") -> 40 | P4: =TEXT(H4,"mmmm") -> February | Q4: =DATEDIF(H4,TODAY(),"y") -> 12 | R4: =IF(AND(O4>25,Q4>2),"Eligible","Not Eligible") -> Eligible | S4: =IF(OR(D4=$D$7,D4=$D$2),"True","False") -> False
A5: EMP015 | B5: Joanne | C5: Macdonald | D5: Marketing | E5: Marketing Officer | F5: 71 | G5: 35168 | H5: 41353 | I5: 4422 | J5: =IF(F5>=50,"Pass","Fail") -> Pass | K5: {=IFS(F5>=90,"Excellent",F5>=70,"Good",F5>=50,"Average",F5<50,"Poor")} -> Good | L5: =LEFT(D5,3) -> Mar | M5: =CONCATENATE(B5," ",C5) -> Joanne Macdonald | N5: =LEN(A5) -> 6 | O5: =DATEDIF(G5,TODAY(),"y") -> 29 | P5: =TEXT(H5,"mmmm") -> March | Q5: =DATEDIF(H5,TODAY(),"y") -> 12 | R5: =IF(AND(O5>25,Q5>2),"Eligible","Not Eligible") -> Eligible | S5: =IF(OR(D5=$D$7,D5=$D$2),"True","False") -> False
A6: EMP104 | B6: Matthew | C6: Frazier | D6: Finance | E6: Accountant | F6: 86 | G6: 34903 | H6: 41368 | I6: 8902 | J6: =IF(F6>=50,"Pass","Fail") -> Pass | K6: {=IFS(F6>=90,"Excellent",F6>=70,"Good",F6>=50,"Average",F6<50,"Poor")} -> Good | L6: =LEFT(D6,3) -> Fin | M6: =CONCATENATE(B6," ",C6) -> Matthew Frazier | N6: =LEN(A6) -> 6 | O6: =DATEDIF(G6,TODAY(),"y") -> 30 | P6: =TEXT(H6,"mmmm") -> April | Q6: =DATEDIF(H6,TODAY(),"y") -> 12 | R6: =IF(AND(O6>25,Q6>2),"Eligible","Not Eligible") -> Eligible | S6: =IF(OR(D6=$D$7,D6=$D$2),"True","False") -> False
A7: EMP014 | B7: Dana | C7: Hancock | D7: HR | E7: HR Manager | F7: 73 | G7: 32734 | H7: 41374 | I7: 5458 | J7: =IF(F7>=50,"Pass","Fail") -> Pass | K7: {=IFS(F7>=90,"Excellent",F7>=70,"Good",F7>=50,"Average",F7<50,"Poor")} -> Good | L7: =LEFT(D7,3) -> HR | M7: =CONCATENATE(B7," ",C7) -> Dana Hancock | N7: =LEN(A7) -> 6 | O7: =DATEDIF(G7,TODAY(),"y") -> 36 | P7: =TEXT(H7,"mmmm") -> April | Q7: =DATEDIF(H7,TODAY(),"y") -> 12 | R7: =IF(AND(O7>25,Q7>2),"Eligible","Not Eligible") -> Eligible | S7: =IF(OR(D7=$D$7,D7=$D$2),"True","False") -> True
A8: EMP137 | B8: Joshua | C8: Torres | D8: Marketing | E8: Brand Manager | F8: 32 | G8: 36779 | H8: 41381 | I8: 7810 | J8: =IF(F8>=50,"Pass","Fail") -> Fail | K8: {=IFS(F8>=90,"Excellent",F8>=70,"Good",F8>=50,"Average",F8<50,"Poor")} -> Poor | L8: =LEFT(D8,3) -> Mar | M8: =CONCATENATE(B8," ",C8) -> Joshua Torres | N8: =LEN(A8) -> 6 | O8: =DATEDIF(G8,TODAY(),"y") -> 25 | P8: =TEXT(H8,"mmmm") -> April | Q8: =DATEDIF(H8,TODAY(),"y") -> 12 | R8: =IF(AND(O8>25,Q8>2),"Eligible","Not Eligible") -> Not Eligible | S8: =IF(OR(D8=$D$7,D8=$D$2),"True","False") -> False
A9: EMP030 | B9: Phillip | C9: Anderson | D9: IT | E9: IT Support | F9: 97 | G9: 34153 | H9: 41419 | I9: 4833 | J9: =IF(F9>=50,"Pass","Fail") -> Pass | K9: {=IFS(F9>=90,"Excellent",F9>=70,"Good",F9>=50,"Average",F9<50,"Poor")} -> Excellent | L9: =LEFT(D9,3) -> IT | M9: =CONCATENATE(B9," ",C9) -> Phillip Anderson | N9: =LEN(A9) -> 6 | O9: =DATEDIF(G9,TODAY(),"y") -> 32 | P9: =TEXT(H9,"mmmm") -> May | Q9: =DATEDIF(H9,TODAY(),"y") -> 12 | R9: =IF(AND(O9>25,Q9>2),"Eligible","Not Eligible") -> Eligible | S9: =IF(OR(D9=$D$7,D9=$D$2),"True","False") -> False
A10: EMP153 | B10: Michael | C10: Fernandez | D10: Finance | E10: Financial Analyst | F10: 64 | G10: 32479 | H10: 41422 | I10: 3454 | J10: =IF(F10>=50,"Pass","Fail") -> Pass | K10: {=IFS(F10>=90,"Excellent",F10>=70,"Good",F10>=50,"Average",F10<50,"Poor")} -> Average | L10: =LEFT(D10,3) -> Fin | M10: =CONCATENATE(B10," ",C10) -> Michael Fernandez | N10: =LEN(A10) -> 6 | O10: =DATEDIF(G10,TODAY(),"y") -> 36 | P10: =TEXT(H10,"mmmm") -> May | Q10: =DATEDIF(H10,TODAY(),"y") -> 12 | R10: =IF(AND(O10>25,Q10>2),"Eligible","Not Eligible") -> Eligible | S10: =IF(OR(D10=$D$7,D10=$D$2),"True","False") -> False
A11: EMP173 | B11: Samantha | C11: Johnson | D11: Finance | E11: Financial Analyst | F11: 92 | G11: 33744 | H11: 41452 | I11: 8674 | J11: =IF(F11>=50,"Pass","Fail") -> Pass | K11: {=IFS(F11>=90,"Excellent",F11>=70,"Good",F11>=50,"Average",F11<50,"Poor")} -> Excellent | L11: =LEFT(D11,3) -> Fin | M11: =CONCATENATE(B11," ",C11) -> Samantha Johnson | N11: =LEN(A11) -> 6 | O11: =DATEDIF(G11,TODAY(),"y") -> 33 | P11: =TEXT(H11,"mmmm") -> June | Q11: =DATEDIF(H11,TODAY(),"y") -> 12 | R11: =IF(AND(O11>25,Q11>2),"Eligible","Not Eligible") -> Eligible | S11: =IF(OR(D11=$D$7,D11=$D$2),"True","False") -> False
A12: EMP183 | B12: Eric | C12: Hughes | D12: Marketing | E12: Marketing Officer | F12: 31 | G12: 34015 | H12: 41503 | I12: 3425 | J12: =IF(F12>=50,"Pass","Fail") -> Fail | K12: {=IFS(F12>=90,"Excellent",F12>=70,"Good",F12>=50,"Average",F12<50,"Poor")} -> Poor | L12: =LEFT(D12,3) -> Mar | M12: =CONCATENATE(B12," ",C12) -> Eric Hughes | N12: =LEN(A12) -> 6 | O12: =DATEDIF(G12,TODAY(),"y") -> 32 | P12: =TEXT(H12,"mmmm") -> August | Q12: =DATEDIF(H12,TODAY(),"y") -> 12 | R12: =IF(AND(O12>25,Q12>2),"Eligible","Not Eligible") -> Eligible | S12: =IF(OR(D12=$D$7,D12=$D$2),"True","False") -> False
A13: EMP160 | B13: Robert | C13: Pierce | D13: IT | E13: System Admin | F13: 57 | G13: 33162 | H13: 41513 | I13: 6780 | J13: =IF(F13>=50,"Pass","Fail") -> Pass | K13: {=IFS(F13>=90,"Excellent",F13>=70,"Good",F13>=50,"Average",F13<50,"Poor")} -> Average | L13: =LEFT(D13,3) -> IT | M13: =CONCATENATE(B13," ",C13) -> Robert Pierce | N13: =LEN(A13) -> 6 | O13: =DATEDIF(G13,TODAY(),"y") -> 35 | P13: =TEXT(H13,"mmmm") -> August | Q13: =DATEDIF(H13,TODAY(),"y") -> 12 | R13: =IF(AND(O13>25,Q13>2),"Eligible","Not Eligible") -> Eligible | S13: =IF(OR(D13=$D$7,D13=$D$2),"True","False") -> False
... A201: EMP158 | B201: Holly | C201: Thompson | D201: Marketing | E201: Brand Manager | F201: 40 | G201: 33864 | H201: 45946 | I201: 7269 | J201: =IF(F201>=50,"Pass","Fail") -> Fail | K201: {=IFS(F201>=90,"Excellent",F201>=70,"Good",F201>=50,"Average",F201<50,"Poor")} -> Poor | L201: =LEFT(D201,3) -> Mar | M201: =CONCATENATE(B201," ",C201) -> Holly Thompson | N201: =LEN(A201) -> 6 | O201: =DATEDIF(G201,TODAY(),"y") -> 33 | P201: =TEXT(H201,"mmmm") -> October | Q201: =DATEDIF(H201,TODAY(),"y") -> 0 | R201: =IF(AND(O201>25,Q201>2),"Eligible","Not Eligible") -> Not Eligible | S201: =IF(OR(D201=$D$7,D201=$D$2),"True","False") -> False

Sheet Department-VLOOKUP
A1: Employee ID | B1: Department Name
A2: EMP001 | B2: =VLOOKUP(A2,'Employee Record'!$A2:$T$201,4,FALSE) -> IT
A3: EMP002 | B3: =VLOOKUP(A3,'Employee Record'!$A3:$T$201,4,FALSE) -> Finance
A4: EMP003 | B4: =VLOOKUP(A4,'Employee Record'!$A4:$T$201,4,FALSE) -> HR
A5: EMP004 | B5: =VLOOKUP(A5,'Employee Record'!$A5:$T$201,4,FALSE) -> Finance
A6: EMP005 | B6: =VLOOKUP(A6,'Employee Record'!$A6:$T$201,4,FALSE) -> Finance
A7: EMP006 | B7: =VLOOKUP(A7,'Employee Record'!$A7:$T$201,4,FALSE) -> Sales
A8: EMP007 | B8: =VLOOKUP(A8,'Employee Record'!$A8:$T$201,4,FALSE) -> IT
A9: EMP008 | B9: =VLOOKUP(A9,'Employee Record'!$A9:$T$201,4,FALSE) -> Sales
A10: EMP009 | B10: =VLOOKUP(A10,'Employee Record'!$A10:$T$201,4,FALSE) -> Finance
A11: EMP010 | B11: =VLOOKUP(A11,'Employee Record'!$A11:$T$201,4,FALSE) -> Finance
A12: EMP011 | B12: =VLOOKUP(A12,'Employee Record'!$A12:$T$201,4,FALSE) -> Finance
A13: EMP012 | B13: =VLOOKUP(A13,'Employee Record'!$A13:$T$201,4,FALSE) -> HR
... A201: EMP200 | B201: =VLOOKUP(A201,'Employee Record'!$A201:$T$201,4,FALSE) -> Marketing

Sheet HLOOKUP
A1: Full Name | B1: Michael Wagner | C1: Adam Henry | D1: Gregory Rojas | E1: Joseph Estrada
A2: Employee ID | B2: EMP001 | C2: EMP002 | D2: EMP003 | E2: EMP004
A3: First Name | B3: Michael | C3: Adam | D3: Gregory | E3: Joseph
A4: Last Name | B4: Wagner | C4: Henry | D4: Rojas | E4: Estrada
A5: Department | B5: IT | C5: Finance | D5: HR | E5: Finance
A6: Job Title | B6: IT Support | C6: Accountant | D6: HR Assistant | E6: Financial Analyst
A7: Performance Score | B7: 85 | C7: 93 | D7: 37 | E7: 87
A8: Date of Birth | B8: 33693 | C8: 32359 | D8: 36559 | E8: 31829
A9: Hire Date | B9: 45252 | C9: 45552 | D9: 43269 | E9: 43487
A10: Salary | B10: 8352 | C10: 5982 | D10: 5767 | E10: 5622
A11: Comments | B11: Pass | C11: Pass | D11: Fail | E11: Pass
A12: Performance Grade | B12: Good | C12: Excellent | D12: Poor | E12: Good
A13: Dept Code | B13: IT | C13: Fin | D13: HR | E13: Fin
A14: Length of Emp ID | B14: 6 | C14: 6 | D14: 6 | E14: 6
A15: Employee Age | B15: 33 | C15: 37 | D15: 25 | E15: 38
A16: Months | B16: November | C16: September | D16: June | E16: January
A17: Employee Year of Service | B17: 1 | C17: 1 | D17: 7 | E17: 6
A18: Eligibily Status | B18: Not Eligible | C18: Not Eligible | D18: Not Eligible | E18: Eligible
A19: Sales/IT | B19: True | C19: False | D19: False | E19: False
A20: Bonus | B20: 4176 | C20: 2991 | D20: 2883.5 | E20: 2811
A22: Full Name | B22: Gregory Rojas
A23: Grade | B23: =HLOOKUP(B22,$A$1:$E$20,13,FALSE) -> HR
E38: ..

Sheet XLOOKUP,INDEX & MATCH
A1: Full Name | B1: Job Title | C1: Performance Score
A2: Michael Wagner | B2: {=XLOOKUP(A2,'Employee Record'!$M$2:$M$201,'Employee Record'!$E$2:$E$201)} -> IT Support | C2: {=INDEX('Employee Record'!$F$2:$F$201,MATCH('Employee Record'!M2,'Employee Record'!$M$2:$M$201,0))} -> 85
A3: Adam Henry | B3: {=XLOOKUP(A3,'Employee Record'!$M$2:$M$201,'Employee Record'!$E$2:$E$201)} -> Accountant | C3: {=INDEX('Employee Record'!$F$2:$F$201,MATCH('Employee Record'!M3,'Employee Record'!$M$2:$M$201,0))} -> 93
A4: Gregory Rojas | B4: {=XLOOKUP(A4,'Employee Record'!$M$2:$M$201,'Employee Record'!$E$2:$E$201)} -> HR Assistant | C4: {=INDEX('Employee Record'!$F$2:$F$201,MATCH('Employee Record'!M4,'Employee Record'!$M$2:$M$201,0))} -> 37
A5: Joseph Estrada | B5: {=XLOOKUP(A5,'Employee Record'!$M$2:$M$201,'Employee Record'!$E$2:$E$201)} -> Financial Analyst | C5: {=INDEX('Employee Record'!$F$2:$F$201,MATCH('Employee Record'!M5,'Employee Record'!$M$2:$M$201,0))} -> 87
A6: Tracie Collins | B6: {=XLOOKUP(A6,'Employee Record'!$M$2:$M$201,'Employee Record'!$E$2:$E$201)} -> Accountant | C6: {=INDEX('Employee Record'!$F$2:$F$201,MATCH('Employee Record'!M6,'Employee Record'!$M$2:$M$201,0))} -> 63
A7: Jonathon Wright | B7: {=XLOOKUP(A7,'Employee Record'!$M$2:$M$201,'Employee Record'!$E$2:$E$201)} -> Sales Rep | C7: {=INDEX('Employee Record'!$F$2:$F$201,MATCH('Employee Record'!M7,'Employee Record'!$M$2:$M$201,0))} -> 35
A8: Christina Haynes | B8: {=XLOOKUP(A8,'Employee Record'!$M$2:$M$201,'Employee Record'!$E$2:$E$201)} -> IT Support | C8: {=INDEX('Employee Record'!$F$2:$F$201,MATCH('Employee Record'!M8,'Employee Record'!$M$2:$M$201,0))} -> 100
A9: Kelly Henry | B9: {=XLOOKUP(A9,'Employee Record'!$M$2:$M$201,'Employee Record'!$E$2:$E$201)} -> Account Exec | C9: {=INDEX('Employee Record'!$F$2:$F$201,MATCH('Employee Record'!M9,'Employee Record'!$M$2:$M$201,0))} -> 65
A10: Mary Torres | B10: {=XLOOKUP(A10,'Employee Record'!$M$2:$M$201,'Employee Record'!$E$2:$E$201)} -> Accountant | C10: {=INDEX('Employee Record'!$F$2:$F$201,MATCH('Employee Record'!M10,'Employee Record'!$M$2:$M$201,0))} -> 64
A11: David Rodriguez | B11: {=XLOOKUP(A11,'Employee Record'!$M$2:$M$201,'Employee Record'!$E$2:$E$201)} -> Accountant | C11: {=INDEX('Employee Record'!$F$2:$F$201,MATCH('Employee Record'!M11,'Employee Record'!$M$2:$M$201,0))} -> 53
A12: John Cole | B12: {=XLOOKUP(A12,'Employee Record'!$M$2:$M$201,'Employee Record'!$E$2:$E$201)} -> Accountant | C12: {=INDEX('Employee Record'!$F$2:$F$201,MATCH('Employee Record'!M12,'Employee Record'!$M$2:$M$201,0))} -> 62
A13: Christina Levine | B13: {=XLOOKUP(A13,'Employee Record'!$M$2:$M$201,'Employee Record'!$E$2:$E$201)} -> HR Assistant | C13: {=INDEX('Employee Record'!$F$2:$F$201,MATCH('Employee Record'!M13,'Employee Record'!$M$2:$M$201,0))} -> 82
... A201: Lisa Smith | B201: {=XLOOKUP(A201,'Employee Record'!$M$2:$M$201,'Employee Record'!$E$2:$E$201)} -> Marketing Officer | C201: {=INDEX('Employee Record'!$F$2:$F$201,MATCH('Employee Record'!M201,'Employee Record'!$M$2:$M$201,0))} -> 45
